<?xml version="1.0" encoding="UTF-8"?>
<PeakList>
  <PeakList1D>
    <PeakList1DHeader creator="nmrsu" date="2022-12-28T02:27:21.841+08:00" expNo="11" name="LXY-1" owner="" procNo="1" source="D:/GYJ/20221227/china">
      <PeakPickDetails>F1=222.707993ppm, F2=-22.707928ppm, MI=0.00cm, MAXI=10000.00cm, PC=1.400
      </PeakPickDetails>
    </PeakList1DHeader>
    <Peak1D F1="141.413422" intensity="8.350350e-01" type="0"/>
    <Peak1D F1="127.274086" intensity="2.950575e+00" type="0"/>
    <Peak1D F1="127.178925" intensity="2.416996e+00" type="0"/>
    <Peak1D F1="126.904007" intensity="1.287947e+00" type="0"/>
    <Peak1D F1="77.653236" intensity="1.422962e+00" type="0"/>
    <Peak1D F1="48.021603" intensity="2.130062e+00" type="0"/>
    <Peak1D F1="47.880474" intensity="5.983022e+00" type="0"/>
    <Peak1D F1="47.739635" intensity="1.214474e+01" type="0"/>
    <Peak1D F1="47.598183" intensity="1.500000e+01" type="0"/>
    <Peak1D F1="47.456409" intensity="1.368988e+01" type="0"/>
    <Peak1D F1="47.314461" intensity="7.300090e+00" type="0"/>
    <Peak1D F1="47.172409" intensity="2.563458e+00" type="0"/>
    <Peak1D F1="-1.442283" intensity="7.482751e-02" type="0"/>
  </PeakList1D>
</PeakList>
